.gitignore
LICENSE
MANIFEST.in
README.md
setup.py
ssh_telegram_advice.epj
etc/ssh_telegram_advice/ssh_telegram_advice.default
init.d/ssh_telegram_advice
locale/en.po
locale/es.po
locale/ssh_telegram_advice.pot
ssh_telegram_advice/__init__.py
ssh_telegram_advice/core.py
ssh_telegram_advice.egg-info/PKG-INFO
ssh_telegram_advice.egg-info/SOURCES.txt
ssh_telegram_advice.egg-info/dependency_links.txt
ssh_telegram_advice.egg-info/entry_points.txt
ssh_telegram_advice.egg-info/not-zip-safe
ssh_telegram_advice.egg-info/top_level.txt
ssh_telegram_advice/locale/en/LC_MESSAGES/ssh_telegram_advice.mo
ssh_telegram_advice/locale/es/LC_MESSAGES/ssh_telegram_advice.mo
ssh_telegram_advice/reusing/datetime_functions.py
ssh_telegram_advice/reusing/file_functions.py
ssh_telegram_advice/reusing/github.py