Metadata-Version: 2.1
Name: ssh-telegram-advice
Version: 0.3.0
Summary: Python app to log in Telegram ssh logins
Home-page: https://github.com/turulomio/ssh_telegram_advice
Author: Turulomio
Author-email: turulomio@yahoo.es
License: GPL-3
Keywords: ssh telegram advice logs
Classifier: Development Status :: 4 - Beta
Classifier: Intended Audience :: Developers
Classifier: Topic :: Software Development :: Build Tools
Classifier: License :: OSI Approved :: GNU General Public License v3 (GPLv3)
Classifier: Programming Language :: Python :: 3
License-File: LICENSE
